portil/__init__.py
portil/portil.py
portil-0.0.1.dist-info/licenses/LICENSE
portil-0.0.1.dist-info/METADATA
portil-0.0.1.dist-info/WHEEL
portil-0.0.1.dist-info/entry_points.txt
portil-0.0.1.dist-info/top_level.txt
portil-0.0.1.dist-info/RECORD
