Metadata-Version: 2.4
Name: portil
Version: 0.0.1
Summary: A cloud-based application port forwarder.
Author: DJ Holt
License:                     GNU GENERAL PUBLIC LICENSE
Project-URL: Homepage, https://github.com/djholt/portil
Classifier: Programming Language :: Python :: 3
Classifier: Operating System :: OS Independent
Requires-Python: >=3.9
License-File: LICENSE
Requires-Dist: paramiko
Requires-Dist: platformdirs
Dynamic: license-file
